coloquinte.py
coloquinte_pybind.cpython-37m-x86_64-linux-gnu.so
coloquinte-0.4.1.dist-info/RECORD
coloquinte-0.4.1.dist-info/WHEEL
coloquinte-0.4.1.dist-info/top_level.txt
coloquinte-0.4.1.dist-info/entry_points.txt
coloquinte-0.4.1.dist-info/METADATA
