Metadata-Version: 2.1
Name: coloquinte
Version: 0.4.1
Summary: Python interface for the Coloquinte VLSI placer
Home-page: https://github.com/Coloquinte/PlaceRoute
Author: Gabriel Gouvine
Author-email: gabriel.gouvine_git@m4x.org
License: MIT
Platform: UNKNOWN
Classifier: License :: OSI Approved :: MIT License
Classifier: Programming Language :: Python :: 3
Classifier: Intended Audience :: Science/Research
Classifier: Intended Audience :: Developers
Classifier: Topic :: Scientific/Engineering :: Electronic Design Automation (EDA)
Requires-Python: >=3.8
